CifFile/cif_files_validator.py
CifFile/YappsStarParser_1_0.py
CifFile/YappsStarParser_1_1.py
CifFile/TypeContentsParser.py
CifFile/YappsStarParser_STAR2.py
CifFile/StarFile.py
CifFile/__init__.py
CifFile/StarScan.cpython-310-darwin.so
CifFile/yapps3_compiled_rt.py
CifFile/YappsStarParser_2_0.py
CifFile/CifFile_module.py
CifFile/drel/drel_ast_yacc.py
CifFile/drel/py_from_ast.py
CifFile/drel/__init__.py
CifFile/drel/drel_lex.py
CifFile/drel/drel_runtime.py
pycifrw-5.0.1.dist-info/RECORD
pycifrw-5.0.1.dist-info/WHEEL
pycifrw-5.0.1.dist-info/top_level.txt
pycifrw-5.0.1.dist-info/METADATA
pycifrw-5.0.1.dist-info/licenses/LICENSE
